aqi/__init__.py
aqi/constants.py
aqi/algos/__init__.py
aqi/algos/base.py
aqi/algos/epa.py
aqi/algos/mep.py
python_aqi-0.6.1.dist-info/DESCRIPTION.rst
python_aqi-0.6.1.dist-info/METADATA
python_aqi-0.6.1.dist-info/RECORD
python_aqi-0.6.1.dist-info/WHEEL
python_aqi-0.6.1.dist-info/entry_points.txt
python_aqi-0.6.1.dist-info/metadata.json
python_aqi-0.6.1.dist-info/top_level.txt
