Metadata-Version: 2.0
Name: python-aqi
Version: 0.6.1
Summary: A library to convert between AQI value and pollutant concentration (µg/m³ or ppm)
Home-page: https://github.com/hrbonz/python-aqi
Author: Stefan "hr" Berder
Author-email: hr@bonz.org
License: BSD 3-Clause
Keywords: air quality pm2.5 EPA MEP
Platform: UNKNOWN
Classifier: Development Status :: 5 - Production/Stable
Classifier: Environment :: Console
Classifier: Intended Audience :: Developers
Classifier: Intended Audience :: Healthcare Industry
Classifier: License :: OSI Approved :: BSD License
Classifier: Programming Language :: Python :: 2.7
Classifier: Programming Language :: Python :: 3.3
